<?xml version="1.0" encoding="UTF-8"?>
<tv generator_info_name="none" generator_info_url="none">
  <channel id="CityNews247Toronto.ca"><display-name lang="en">City News 24/7</display-name></channel>
  <programme start="20250429140000 -0400" stop="20250429150000 -0400" channel="CityNews247Toronto.ca"><title>City News 24/7 at 2</title><desc>Toronto's breaking news, including the latest updates on weather, traffic, transit, sports, and stocks.</desc></programme>
  <programme start="20250429150000 -0400" stop="20250429160000 -0400" channel="CityNews247Toronto.ca"><title>City News 24/7 at 3</title><desc>Toronto's breaking news, including the latest updates on weather, traffic, transit, sports, and stocks.</desc></programme>
  <programme start="20250429160000 -0400" stop="20250429170000 -0400" channel="CityNews247Toronto.ca"><title>City News 24/7 at 4</title><desc>Toronto's breaking news, including the latest updates on weather, traffic, transit, sports, and stocks.</desc></programme>
  <programme start="20250429170000 -0400" stop="20250429180000 -0400" channel="CityNews247Toronto.ca"><title>City News 24/7 at 5</title><desc>Toronto's breaking news, including the latest updates on weather, traffic, transit, sports, and stocks.</desc></programme>
  <programme start="20250429180000 -0400" stop="20250429190000 -0400" channel="CityNews247Toronto.ca"><title>City News 24/7 at 6</title><desc>Toronto's breaking news, including the latest updates on weather, traffic, transit, sports, and stocks.</desc></programme>
  <programme start="20250429190000 -0400" stop="20250429200000 -0400" channel="CityNews247Toronto.ca"><title>City News 24/7 at 7</title><desc>Toronto's breaking news, including the latest updates on weather, traffic, transit, sports, and stocks.</desc></programme>
  <programme start="20250429200000 -0400" stop="20250429210000 -0400" channel="CityNews247Toronto.ca"><title>City News 24/7 at 8</title><desc>Toronto's breaking news, including the latest updates on weather, traffic, transit, sports, and stocks.</desc></programme>
  <programme start="20250429210000 -0400" stop="20250429220000 -0400" channel="CityNews247Toronto.ca"><title>City News 24/7 at 9</title><desc>Toronto's breaking news, including the latest updates on weather, traffic, transit, sports, and stocks.</desc></programme>
  <programme start="20250429220000 -0400" stop="20250429230000 -0400" channel="CityNews247Toronto.ca"><title>City News 24/7 at 10</title><desc>Toronto's breaking news, including the latest updates on weather, traffic, transit, sports, and stocks.</desc></programme>
  <programme start="20250429230000 -0400" stop="20250430000000 -0400" channel="CityNews247Toronto.ca"><title>City News 24/7 at 11</title><desc>Toronto's breaking news, including the latest updates on weather, traffic, transit, sports, and stocks.</desc></programme>
  <programme start="20250430000000 -0400" stop="20250430010000 -0400" channel="CityNews247Toronto.ca"><title>City News 24/7 at 12</title><desc>Toronto's breaking news, including the latest updates on weather, traffic, transit, sports, and stocks.</desc></programme>
  <programme start="20250430010000 -0400" stop="20250430020000 -0400" channel="CityNews247Toronto.ca"><title>City News 24/7 at 1</title><desc>Toronto's breaking news, including the latest updates on weather, traffic, transit, sports, and stocks.</desc></programme>
  <programme start="20250430020000 -0400" stop="20250430030000 -0400" channel="CityNews247Toronto.ca"><title>City News 24/7 at 2</title><desc>Toronto's breaking news, including the latest updates on weather, traffic, transit, sports, and stocks.</desc></programme>
  <programme start="20250430030000 -0400" stop="20250430040000 -0400" channel="CityNews247Toronto.ca"><title>City News 24/7 at 3</title><desc>Toronto's breaking news, including the latest updates on weather, traffic, transit, sports, and stocks.</desc></programme>
  <programme start="20250430040000 -0400" stop="20250430050000 -0400" channel="CityNews247Toronto.ca"><title>City News 24/7 at 4</title><desc>Toronto's breaking news, including the latest updates on weather, traffic, transit, sports, and stocks.</desc></programme>
  <programme start="20250430050000 -0400" stop="20250430060000 -0400" channel="CityNews247Toronto.ca"><title>City News 24/7 at 5</title><desc>Toronto's breaking news, including the latest updates on weather, traffic, transit, sports, and stocks.</desc></programme>
  <programme start="20250430060000 -0400" stop="20250430070000 -0400" channel="CityNews247Toronto.ca"><title>City News 24/7 at 6</title><desc>Toronto's breaking news, including the latest updates on weather, traffic, transit, sports, and stocks.</desc></programme>
  <programme start="20250430070000 -0400" stop="20250430080000 -0400" channel="CityNews247Toronto.ca"><title>City News 24/7 at 7</title><desc>Toronto's breaking news, including the latest updates on weather, traffic, transit, sports, and stocks.</desc></programme>
  <programme start="20250430080000 -0400" stop="20250430090000 -0400" channel="CityNews247Toronto.ca"><title>City News 24/7 at 8</title><desc>Toronto's breaking news, including the latest updates on weather, traffic, transit, sports, and stocks.</desc></programme>
  <programme start="20250430090000 -0400" stop="20250430100000 -0400" channel="CityNews247Toronto.ca"><title>City News 24/7 at 9</title><desc>Toronto's breaking news, including the latest updates on weather, traffic, transit, sports, and stocks.</desc></programme>
  <programme start="20250430100000 -0400" stop="20250430110000 -0400" channel="CityNews247Toronto.ca"><title>City News 24/7 at 10</title><desc>Toronto's breaking news, including the latest updates on weather, traffic, transit, sports, and stocks.</desc></programme>
  <programme start="20250430110000 -0400" stop="20250430120000 -0400" channel="CityNews247Toronto.ca"><title>City News 24/7 at 11</title><desc>Toronto's breaking news, including the latest updates on weather, traffic, transit, sports, and stocks.</desc></programme>
  <programme start="20250430120000 -0400" stop="20250430130000 -0400" channel="CityNews247Toronto.ca"><title>City News 24/7 at 12</title><desc>Toronto's breaking news, including the latest updates on weather, traffic, transit, sports, and stocks.</desc></programme>
  <programme start="20250430130000 -0400" stop="20250430140000 -0400" channel="CityNews247Toronto.ca"><title>City News 24/7 at 1</title><desc>Toronto's breaking news, including the latest updates on weather, traffic, transit, sports, and stocks.</desc></programme>
  <programme start="20250430140000 -0400" stop="20250430150000 -0400" channel="CityNews247Toronto.ca"><title>City News 24/7 at 2</title><desc>Toronto's breaking news, including the latest updates on weather, traffic, transit, sports, and stocks.</desc></programme>
  <programme start="20250430150000 -0400" stop="20250430160000 -0400" channel="CityNews247Toronto.ca"><title>City News 24/7 at 3</title><desc>Toronto's breaking news, including the latest updates on weather, traffic, transit, sports, and stocks.</desc></programme>
  <programme start="20250430160000 -0400" stop="20250430170000 -0400" channel="CityNews247Toronto.ca"><title>City News 24/7 at 4</title><desc>Toronto's breaking news, including the latest updates on weather, traffic, transit, sports, and stocks.</desc></programme>
  <programme start="20250430170000 -0400" stop="20250430180000 -0400" channel="CityNews247Toronto.ca"><title>City News 24/7 at 5</title><desc>Toronto's breaking news, including the latest updates on weather, traffic, transit, sports, and stocks.</desc></programme>
  <programme start="20250430180000 -0400" stop="20250430190000 -0400" channel="CityNews247Toronto.ca"><title>City News 24/7 at 6</title><desc>Toronto's breaking news, including the latest updates on weather, traffic, transit, sports, and stocks.</desc></programme>
  <programme start="20250430190000 -0400" stop="20250430200000 -0400" channel="CityNews247Toronto.ca"><title>City News 24/7 at 7</title><desc>Toronto's breaking news, including the latest updates on weather, traffic, transit, sports, and stocks.</desc></programme>
  <programme start="20250430200000 -0400" stop="20250430210000 -0400" channel="CityNews247Toronto.ca"><title>City News 24/7 at 8</title><desc>Toronto's breaking news, including the latest updates on weather, traffic, transit, sports, and stocks.</desc></programme>
  <programme start="20250430210000 -0400" stop="20250430220000 -0400" channel="CityNews247Toronto.ca"><title>City News 24/7 at 9</title><desc>Toronto's breaking news, including the latest updates on weather, traffic, transit, sports, and stocks.</desc></programme>
  <programme start="20250430220000 -0400" stop="20250430230000 -0400" channel="CityNews247Toronto.ca"><title>City News 24/7 at 10</title><desc>Toronto's breaking news, including the latest updates on weather, traffic, transit, sports, and stocks.</desc></programme>
  <programme start="20250430230000 -0400" stop="20250501000000 -0400" channel="CityNews247Toronto.ca"><title>City News 24/7 at 11</title><desc>Toronto's breaking news, including the latest updates on weather, traffic, transit, sports, and stocks.</desc></programme>
  <programme start="20250501000000 -0400" stop="20250501010000 -0400" channel="CityNews247Toronto.ca"><title>City News 24/7 at 12</title><desc>Toronto's breaking news, including the latest updates on weather, traffic, transit, sports, and stocks.</desc></programme>
  <programme start="20250501010000 -0400" stop="20250501020000 -0400" channel="CityNews247Toronto.ca"><title>City News 24/7 at 1</title><desc>Toronto's breaking news, including the latest updates on weather, traffic, transit, sports, and stocks.</desc></programme>
  <programme start="20250501020000 -0400" stop="20250501030000 -0400" channel="CityNews247Toronto.ca"><title>City News 24/7 at 2</title><desc>Toronto's breaking news, including the latest updates on weather, traffic, transit, sports, and stocks.</desc></programme>
  <programme start="20250501030000 -0400" stop="20250501040000 -0400" channel="CityNews247Toronto.ca"><title>City News 24/7 at 3</title><desc>Toronto's breaking news, including the latest updates on weather, traffic, transit, sports, and stocks.</desc></programme>
  <programme start="20250501040000 -0400" stop="20250501050000 -0400" channel="CityNews247Toronto.ca"><title>City News 24/7 at 4</title><desc>Toronto's breaking news, including the latest updates on weather, traffic, transit, sports, and stocks.</desc></programme>
  <programme start="20250501050000 -0400" stop="20250501060000 -0400" channel="CityNews247Toronto.ca"><title>City News 24/7 at 5</title><desc>Toronto's breaking news, including the latest updates on weather, traffic, transit, sports, and stocks.</desc></programme>
  <programme start="20250501060000 -0400" stop="20250501070000 -0400" channel="CityNews247Toronto.ca"><title>City News 24/7 at 6</title><desc>Toronto's breaking news, including the latest updates on weather, traffic, transit, sports, and stocks.</desc></programme>
  <programme start="20250501070000 -0400" stop="20250501080000 -0400" channel="CityNews247Toronto.ca"><title>City News 24/7 at 7</title><desc>Toronto's breaking news, including the latest updates on weather, traffic, transit, sports, and stocks.</desc></programme>
  <programme start="20250501080000 -0400" stop="20250501090000 -0400" channel="CityNews247Toronto.ca"><title>City News 24/7 at 8</title><desc>Toronto's breaking news, including the latest updates on weather, traffic, transit, sports, and stocks.</desc></programme>
  <programme start="20250501090000 -0400" stop="20250501100000 -0400" channel="CityNews247Toronto.ca"><title>City News 24/7 at 9</title><desc>Toronto's breaking news, including the latest updates on weather, traffic, transit, sports, and stocks.</desc></programme>
  <programme start="20250501100000 -0400" stop="20250501110000 -0400" channel="CityNews247Toronto.ca"><title>City News 24/7 at 10</title><desc>Toronto's breaking news, including the latest updates on weather, traffic, transit, sports, and stocks.</desc></programme>
  <programme start="20250501110000 -0400" stop="20250501120000 -0400" channel="CityNews247Toronto.ca"><title>City News 24/7 at 11</title><desc>Toronto's breaking news, including the latest updates on weather, traffic, transit, sports, and stocks.</desc></programme>
  <programme start="20250501120000 -0400" stop="20250501130000 -0400" channel="CityNews247Toronto.ca"><title>City News 24/7 at 12</title><desc>Toronto's breaking news, including the latest updates on weather, traffic, transit, sports, and stocks.</desc></programme>
  <programme start="20250501130000 -0400" stop="20250501140000 -0400" channel="CityNews247Toronto.ca"><title>City News 24/7 at 1</title><desc>Toronto's breaking news, including the latest updates on weather, traffic, transit, sports, and stocks.</desc></programme>
  <programme start="20250501140000 -0400" stop="20250501150000 -0400" channel="CityNews247Toronto.ca"><title>City News 24/7 at 2</title><desc>Toronto's breaking news, including the latest updates on weather, traffic, transit, sports, and stocks.</desc></programme>
  <programme start="20250501150000 -0400" stop="20250501160000 -0400" channel="CityNews247Toronto.ca"><title>City News 24/7 at 3</title><desc>Toronto's breaking news, including the latest updates on weather, traffic, transit, sports, and stocks.</desc></programme>
  <programme start="20250501160000 -0400" stop="20250501170000 -0400" channel="CityNews247Toronto.ca"><title>City News 24/7 at 4</title><desc>Toronto's breaking news, including the latest updates on weather, traffic, transit, sports, and stocks.</desc></programme>
  <programme start="20250501170000 -0400" stop="20250501180000 -0400" channel="CityNews247Toronto.ca"><title>City News 24/7 at 5</title><desc>Toronto's breaking news, including the latest updates on weather, traffic, transit, sports, and stocks.</desc></programme>
  <programme start="20250501180000 -0400" stop="20250501190000 -0400" channel="CityNews247Toronto.ca"><title>City News 24/7 at 6</title><desc>Toronto's breaking news, including the latest updates on weather, traffic, transit, sports, and stocks.</desc></programme>
  <programme start="20250501190000 -0400" stop="20250501200000 -0400" channel="CityNews247Toronto.ca"><title>City News 24/7 at 7</title><desc>Toronto's breaking news, including the latest updates on weather, traffic, transit, sports, and stocks.</desc></programme>
  <programme start="20250501200000 -0400" stop="20250501210000 -0400" channel="CityNews247Toronto.ca"><title>City News 24/7 at 8</title><desc>Toronto's breaking news, including the latest updates on weather, traffic, transit, sports, and stocks.</desc></programme>
  <programme start="20250501210000 -0400" stop="20250501220000 -0400" channel="CityNews247Toronto.ca"><title>City News 24/7 at 9</title><desc>Toronto's breaking news, including the latest updates on weather, traffic, transit, sports, and stocks.</desc></programme>
  <programme start="20250501220000 -0400" stop="20250501230000 -0400" channel="CityNews247Toronto.ca"><title>City News 24/7 at 10</title><desc>Toronto's breaking news, including the latest updates on weather, traffic, transit, sports, and stocks.</desc></programme>
  <programme start="20250501230000 -0400" stop="20250502000000 -0400" channel="CityNews247Toronto.ca"><title>City News 24/7 at 11</title><desc>Toronto's breaking news, including the latest updates on weather, traffic, transit, sports, and stocks.</desc></programme>
  <programme start="20250502000000 -0400" stop="20250502010000 -0400" channel="CityNews247Toronto.ca"><title>City News 24/7 at 12</title><desc>Toronto's breaking news, including the latest updates on weather, traffic, transit, sports, and stocks.</desc></programme>
  <programme start="20250502010000 -0400" stop="20250502020000 -0400" channel="CityNews247Toronto.ca"><title>City News 24/7 at 1</title><desc>Toronto's breaking news, including the latest updates on weather, traffic, transit, sports, and stocks.</desc></programme>
  <programme start="20250502020000 -0400" stop="20250502030000 -0400" channel="CityNews247Toronto.ca"><title>City News 24/7 at 2</title><desc>Toronto's breaking news, including the latest updates on weather, traffic, transit, sports, and stocks.</desc></programme>
  <programme start="20250502030000 -0400" stop="20250502040000 -0400" channel="CityNews247Toronto.ca"><title>City News 24/7 at 3</title><desc>Toronto's breaking news, including the latest updates on weather, traffic, transit, sports, and stocks.</desc></programme>
  <programme start="20250502040000 -0400" stop="20250502050000 -0400" channel="CityNews247Toronto.ca"><title>City News 24/7 at 4</title><desc>Toronto's breaking news, including the latest updates on weather, traffic, transit, sports, and stocks.</desc></programme>
  <programme start="20250502050000 -0400" stop="20250502060000 -0400" channel="CityNews247Toronto.ca"><title>City News 24/7 at 5</title><desc>Toronto's breaking news, including the latest updates on weather, traffic, transit, sports, and stocks.</desc></programme>
  <programme start="20250502060000 -0400" stop="20250502070000 -0400" channel="CityNews247Toronto.ca"><title>City News 24/7 at 6</title><desc>Toronto's breaking news, including the latest updates on weather, traffic, transit, sports, and stocks.</desc></programme>
  <programme start="20250502070000 -0400" stop="20250502080000 -0400" channel="CityNews247Toronto.ca"><title>City News 24/7 at 7</title><desc>Toronto's breaking news, including the latest updates on weather, traffic, transit, sports, and stocks.</desc></programme>
  <programme start="20250502080000 -0400" stop="20250502090000 -0400" channel="CityNews247Toronto.ca"><title>City News 24/7 at 8</title><desc>Toronto's breaking news, including the latest updates on weather, traffic, transit, sports, and stocks.</desc></programme>
  <programme start="20250502090000 -0400" stop="20250502100000 -0400" channel="CityNews247Toronto.ca"><title>City News 24/7 at 9</title><desc>Toronto's breaking news, including the latest updates on weather, traffic, transit, sports, and stocks.</desc></programme>
  <programme start="20250502100000 -0400" stop="20250502110000 -0400" channel="CityNews247Toronto.ca"><title>City News 24/7 at 10</title><desc>Toronto's breaking news, including the latest updates on weather, traffic, transit, sports, and stocks.</desc></programme>
  <programme start="20250502110000 -0400" stop="20250502120000 -0400" channel="CityNews247Toronto.ca"><title>City News 24/7 at 11</title><desc>Toronto's breaking news, including the latest updates on weather, traffic, transit, sports, and stocks.</desc></programme>
  <programme start="20250502120000 -0400" stop="20250502130000 -0400" channel="CityNews247Toronto.ca"><title>City News 24/7 at 12</title><desc>Toronto's breaking news, including the latest updates on weather, traffic, transit, sports, and stocks.</desc></programme>
  <programme start="20250502130000 -0400" stop="20250502140000 -0400" channel="CityNews247Toronto.ca"><title>City News 24/7 at 1</title><desc>Toronto's breaking news, including the latest updates on weather, traffic, transit, sports, and stocks.</desc></programme>
  <programme start="20250502140000 -0400" stop="20250502150000 -0400" channel="CityNews247Toronto.ca"><title>City News 24/7 at 2</title><desc>Toronto's breaking news, including the latest updates on weather, traffic, transit, sports, and stocks.</desc></programme>
  <programme start="20250502150000 -0400" stop="20250502160000 -0400" channel="CityNews247Toronto.ca"><title>City News 24/7 at 3</title><desc>Toronto's breaking news, including the latest updates on weather, traffic, transit, sports, and stocks.</desc></programme>
  <programme start="20250502160000 -0400" stop="20250502170000 -0400" channel="CityNews247Toronto.ca"><title>City News 24/7 at 4</title><desc>Toronto's breaking news, including the latest updates on weather, traffic, transit, sports, and stocks.</desc></programme>
  <programme start="20250502170000 -0400" stop="20250502180000 -0400" channel="CityNews247Toronto.ca"><title>City News 24/7 at 5</title><desc>Toronto's breaking news, including the latest updates on weather, traffic, transit, sports, and stocks.</desc></programme>
  <programme start="20250502180000 -0400" stop="20250502190000 -0400" channel="CityNews247Toronto.ca"><title>City News 24/7 at 6</title><desc>Toronto's breaking news, including the latest updates on weather, traffic, transit, sports, and stocks.</desc></programme>
  <programme start="20250502190000 -0400" stop="20250502200000 -0400" channel="CityNews247Toronto.ca"><title>City News 24/7 at 7</title><desc>Toronto's breaking news, including the latest updates on weather, traffic, transit, sports, and stocks.</desc></programme>
  <programme start="20250502200000 -0400" stop="20250502210000 -0400" channel="CityNews247Toronto.ca"><title>City News 24/7 at 8</title><desc>Toronto's breaking news, including the latest updates on weather, traffic, transit, sports, and stocks.</desc></programme>
  <programme start="20250502210000 -0400" stop="20250502220000 -0400" channel="CityNews247Toronto.ca"><title>City News 24/7 at 9</title><desc>Toronto's breaking news, including the latest updates on weather, traffic, transit, sports, and stocks.</desc></programme>
  <programme start="20250502220000 -0400" stop="20250502230000 -0400" channel="CityNews247Toronto.ca"><title>City News 24/7 at 10</title><desc>Toronto's breaking news, including the latest updates on weather, traffic, transit, sports, and stocks.</desc></programme>
  <programme start="20250502230000 -0400" stop="20250503000000 -0400" channel="CityNews247Toronto.ca"><title>City News 24/7 at 11</title><desc>Toronto's breaking news, including the latest updates on weather, traffic, transit, sports, and stocks.</desc></programme>
  <programme start="20250503000000 -0400" stop="20250503010000 -0400" channel="CityNews247Toronto.ca"><title>City News 24/7 at 12</title><desc>Toronto's breaking news, including the latest updates on weather, traffic, transit, sports, and stocks.</desc></programme>
  <programme start="20250503010000 -0400" stop="20250503020000 -0400" channel="CityNews247Toronto.ca"><title>City News 24/7 at 1</title><desc>Toronto's breaking news, including the latest updates on weather, traffic, transit, sports, and stocks.</desc></programme>
  <programme start="20250503020000 -0400" stop="20250503030000 -0400" channel="CityNews247Toronto.ca"><title>City News 24/7 at 2</title><desc>Toronto's breaking news, including the latest updates on weather, traffic, transit, sports, and stocks.</desc></programme>
  <programme start="20250503030000 -0400" stop="20250503040000 -0400" channel="CityNews247Toronto.ca"><title>City News 24/7 at 3</title><desc>Toronto's breaking news, including the latest updates on weather, traffic, transit, sports, and stocks.</desc></programme>
  <programme start="20250503040000 -0400" stop="20250503050000 -0400" channel="CityNews247Toronto.ca"><title>City News 24/7 at 4</title><desc>Toronto's breaking news, including the latest updates on weather, traffic, transit, sports, and stocks.</desc></programme>
  <programme start="20250503050000 -0400" stop="20250503060000 -0400" channel="CityNews247Toronto.ca"><title>City News 24/7 at 5</title><desc>Toronto's breaking news, including the latest updates on weather, traffic, transit, sports, and stocks.</desc></programme>
  <programme start="20250503060000 -0400" stop="20250503070000 -0400" channel="CityNews247Toronto.ca"><title>City News 24/7 at 6</title><desc>Toronto's breaking news, including the latest updates on weather, traffic, transit, sports, and stocks.</desc></programme>
  <programme start="20250503070000 -0400" stop="20250503080000 -0400" channel="CityNews247Toronto.ca"><title>City News 24/7 at 7</title><desc>Toronto's breaking news, including the latest updates on weather, traffic, transit, sports, and stocks.</desc></programme>
  <programme start="20250503080000 -0400" stop="20250503090000 -0400" channel="CityNews247Toronto.ca"><title>City News 24/7 at 8</title><desc>Toronto's breaking news, including the latest updates on weather, traffic, transit, sports, and stocks.</desc></programme>
  <programme start="20250503090000 -0400" stop="20250503100000 -0400" channel="CityNews247Toronto.ca"><title>City News 24/7 at 9</title><desc>Toronto's breaking news, including the latest updates on weather, traffic, transit, sports, and stocks.</desc></programme>
  <programme start="20250503100000 -0400" stop="20250503110000 -0400" channel="CityNews247Toronto.ca"><title>City News 24/7 at 10</title><desc>Toronto's breaking news, including the latest updates on weather, traffic, transit, sports, and stocks.</desc></programme>
  <programme start="20250503110000 -0400" stop="20250503120000 -0400" channel="CityNews247Toronto.ca"><title>City News 24/7 at 11</title><desc>Toronto's breaking news, including the latest updates on weather, traffic, transit, sports, and stocks.</desc></programme>
  <programme start="20250503120000 -0400" stop="20250503130000 -0400" channel="CityNews247Toronto.ca"><title>City News 24/7 at 12</title><desc>Toronto's breaking news, including the latest updates on weather, traffic, transit, sports, and stocks.</desc></programme>
  <programme start="20250503130000 -0400" stop="20250503140000 -0400" channel="CityNews247Toronto.ca"><title>City News 24/7 at 1</title><desc>Toronto's breaking news, including the latest updates on weather, traffic, transit, sports, and stocks.</desc></programme>
  <programme start="20250503140000 -0400" stop="20250503150000 -0400" channel="CityNews247Toronto.ca"><title>City News 24/7 at 2</title><desc>Toronto's breaking news, including the latest updates on weather, traffic, transit, sports, and stocks.</desc></programme>
  <programme start="20250503150000 -0400" stop="20250503160000 -0400" channel="CityNews247Toronto.ca"><title>City News 24/7 at 3</title><desc>Toronto's breaking news, including the latest updates on weather, traffic, transit, sports, and stocks.</desc></programme>
  <programme start="20250503160000 -0400" stop="20250503170000 -0400" channel="CityNews247Toronto.ca"><title>City News 24/7 at 4</title><desc>Toronto's breaking news, including the latest updates on weather, traffic, transit, sports, and stocks.</desc></programme>
  <programme start="20250503170000 -0400" stop="20250503180000 -0400" channel="CityNews247Toronto.ca"><title>City News 24/7 at 5</title><desc>Toronto's breaking news, including the latest updates on weather, traffic, transit, sports, and stocks.</desc></programme>
  <programme start="20250503180000 -0400" stop="20250503190000 -0400" channel="CityNews247Toronto.ca"><title>City News 24/7 at 6</title><desc>Toronto's breaking news, including the latest updates on weather, traffic, transit, sports, and stocks.</desc></programme>
  <programme start="20250503190000 -0400" stop="20250503200000 -0400" channel="CityNews247Toronto.ca"><title>City News 24/7 at 7</title><desc>Toronto's breaking news, including the latest updates on weather, traffic, transit, sports, and stocks.</desc></programme>
  <programme start="20250503200000 -0400" stop="20250503210000 -0400" channel="CityNews247Toronto.ca"><title>City News 24/7 at 8</title><desc>Toronto's breaking news, including the latest updates on weather, traffic, transit, sports, and stocks.</desc></programme>
  <programme start="20250503210000 -0400" stop="20250503220000 -0400" channel="CityNews247Toronto.ca"><title>City News 24/7 at 9</title><desc>Toronto's breaking news, including the latest updates on weather, traffic, transit, sports, and stocks.</desc></programme>
  <programme start="20250503220000 -0400" stop="20250503230000 -0400" channel="CityNews247Toronto.ca"><title>City News 24/7 at 10</title><desc>Toronto's breaking news, including the latest updates on weather, traffic, transit, sports, and stocks.</desc></programme>
  <programme start="20250503230000 -0400" stop="20250504000000 -0400" channel="CityNews247Toronto.ca"><title>City News 24/7 at 11</title><desc>Toronto's breaking news, including the latest updates on weather, traffic, transit, sports, and stocks.</desc></programme>
  <programme start="20250504000000 -0400" stop="20250504010000 -0400" channel="CityNews247Toronto.ca"><title>City News 24/7 at 12</title><desc>Toronto's breaking news, including the latest updates on weather, traffic, transit, sports, and stocks.</desc></programme>
  <programme start="20250504010000 -0400" stop="20250504020000 -0400" channel="CityNews247Toronto.ca"><title>City News 24/7 at 1</title><desc>Toronto's breaking news, including the latest updates on weather, traffic, transit, sports, and stocks.</desc></programme>
  <programme start="20250504020000 -0400" stop="20250504030000 -0400" channel="CityNews247Toronto.ca"><title>City News 24/7 at 2</title><desc>Toronto's breaking news, including the latest updates on weather, traffic, transit, sports, and stocks.</desc></programme>
  <programme start="20250504030000 -0400" stop="20250504040000 -0400" channel="CityNews247Toronto.ca"><title>City News 24/7 at 3</title><desc>Toronto's breaking news, including the latest updates on weather, traffic, transit, sports, and stocks.</desc></programme>
  <programme start="20250504040000 -0400" stop="20250504050000 -0400" channel="CityNews247Toronto.ca"><title>City News 24/7 at 4</title><desc>Toronto's breaking news, including the latest updates on weather, traffic, transit, sports, and stocks.</desc></programme>
  <programme start="20250504050000 -0400" stop="20250504060000 -0400" channel="CityNews247Toronto.ca"><title>City News 24/7 at 5</title><desc>Toronto's breaking news, including the latest updates on weather, traffic, transit, sports, and stocks.</desc></programme>
  <programme start="20250504060000 -0400" stop="20250504070000 -0400" channel="CityNews247Toronto.ca"><title>City News 24/7 at 6</title><desc>Toronto's breaking news, including the latest updates on weather, traffic, transit, sports, and stocks.</desc></programme>
  <programme start="20250504070000 -0400" stop="20250504080000 -0400" channel="CityNews247Toronto.ca"><title>City News 24/7 at 7</title><desc>Toronto's breaking news, including the latest updates on weather, traffic, transit, sports, and stocks.</desc></programme>
  <programme start="20250504080000 -0400" stop="20250504090000 -0400" channel="CityNews247Toronto.ca"><title>City News 24/7 at 8</title><desc>Toronto's breaking news, including the latest updates on weather, traffic, transit, sports, and stocks.</desc></programme>
  <programme start="20250504090000 -0400" stop="20250504100000 -0400" channel="CityNews247Toronto.ca"><title>City News 24/7 at 9</title><desc>Toronto's breaking news, including the latest updates on weather, traffic, transit, sports, and stocks.</desc></programme>
  <programme start="20250504100000 -0400" stop="20250504110000 -0400" channel="CityNews247Toronto.ca"><title>City News 24/7 at 10</title><desc>Toronto's breaking news, including the latest updates on weather, traffic, transit, sports, and stocks.</desc></programme>
  <programme start="20250504110000 -0400" stop="20250504120000 -0400" channel="CityNews247Toronto.ca"><title>City News 24/7 at 11</title><desc>Toronto's breaking news, including the latest updates on weather, traffic, transit, sports, and stocks.</desc></programme>
  <programme start="20250504120000 -0400" stop="20250504130000 -0400" channel="CityNews247Toronto.ca"><title>City News 24/7 at 12</title><desc>Toronto's breaking news, including the latest updates on weather, traffic, transit, sports, and stocks.</desc></programme>
  <programme start="20250504130000 -0400" stop="20250504140000 -0400" channel="CityNews247Toronto.ca"><title>City News 24/7 at 1</title><desc>Toronto's breaking news, including the latest updates on weather, traffic, transit, sports, and stocks.</desc></programme>
</tv>